pyccb/__init__.py
pyccb/__main__.py
pyccb/generate.py
pyccb/parser.py
pyccb/utils.py
pyccb-0.1.2.dist-info/licenses/LICENSE
pyccb-0.1.2.dist-info/METADATA
pyccb-0.1.2.dist-info/WHEEL
pyccb-0.1.2.dist-info/entry_points.txt
pyccb-0.1.2.dist-info/top_level.txt
pyccb-0.1.2.dist-info/RECORD
