Metadata-Version: 2.4
Name: pyccb
Version: 0.1.2
Summary: Python Compiler Collection for Bash
Author: simplyrohan
License-Expression: GPL-3.0-or-later
Project-URL: Homepage, https://github.com/simplyrohan/pyccb
Project-URL: Repository, https://github.com/simplyrohan/pyccb
Requires-Python: >=3.9
License-File: LICENSE
Dynamic: license-file
